djelmah/__init__.py
djelmah/admin.py
djelmah/api.py
djelmah/apps.py
djelmah/auth.py
djelmah/middleware.py
djelmah/models.py
djelmah/resources.py
djelmah/tests.py
djelmah/urls.py
djelmah/views.py
djelmah/migrations/0001_initial.py
djelmah/migrations/0002_auto_20210126_1447.py
djelmah/migrations/__init__.py
djelmah/static/djelmah/script.min.js
djelmah/templates/djelmah/base.html
djelmah/templates/djelmah/bundle.html
djelmah/templates/djelmah/keys.html
djelmah/templates/djelmah/login.html
djelmah/templates/djelmah/logs.html
django_elmah-1.1.dist-info/LICENSE
django_elmah-1.1.dist-info/METADATA
django_elmah-1.1.dist-info/WHEEL
django_elmah-1.1.dist-info/top_level.txt
django_elmah-1.1.dist-info/RECORD
