Metadata-Version: 2.1
Name: django-elmah
Version: 1.1
Summary: Django Error Logging Modules and Handlers
Home-page: https://github.com/rickjordan/django-elmah
Author: Rick Jordan
Author-email: jordan.rick.d@gmail.com
License: GNU Affero General Public License v3
Platform: UNKNOWN
Classifier: Environment :: Web Environment
Classifier: Framework :: Django
Classifier: Intended Audience :: Developers
Classifier: License :: OSI Approved :: GNU Affero General Public License v3
Classifier: Natural Language :: English
Classifier: Operating System :: OS Independent
Classifier: Programming Language :: Python
Requires-Dist: django-tastypie
Requires-Dist: requests
